{
  "is_valid": true,
  "reason": "Valid CFST physical experiment paper with axial and eccentric short-column tests (10+11 specimens).",
  "ref_info": {
    "title": "薄壁钢管混凝土短柱基本力学性能研究",
    "authors": [
      "金周"
    ],
    "journal": "华侨大学硕士学位论文",
    "year": 2008
  },
  "Group_A": [
    {
      "ref_no": "",
      "specimen_label": "UCFT16",
      "fc_value": 57.8,
      "fc_type": "cube",
      "fy": 318.5,
      "fcy150": "",
      "r_ratio": 0,
      "b": 160.2,
      "h": 161.7,
      "t": 1.98,
      "r0": 0,
      "L": 519.0,
      "e1": 0,
      "e2": 0,
      "n_exp": 1124.0,
      "source_evidence": "Page [28], Table [2-1, 3-1]; setup=images/bc93b79be65b77739c8b6e10aa37c9628bed7d4450e4ab3ce3e9965334e94896.jpg|images/67eaeb8e8af1df4c8801df138bbbc56c7763238f3eb5c9f07387ce8202d15f90.jpg; table=table/表 2-1 轴压试件截面明细表.jpg|table/表 3-1 薄壁钢管混凝土轴压试件一览.jpg"
    },
    {
      "ref_no": "",
      "specimen_label": "SCFT16-1",
      "fc_value": 57.8,
      "fc_type": "cube",
      "fy": 318.5,
      "fcy150": "",
      "r_ratio": 0,
      "b": 160.4,
      "h": 161.6,
      "t": 1.98,
      "r0": 0,
      "L": 519.0,
      "e1": 0,
      "e2": 0,
      "n_exp": 1273.0,
      "source_evidence": "Page [28], Table [2-1, 3-1]; setup=images/bc93b79be65b77739c8b6e10aa37c9628bed7d4450e4ab3ce3e9965334e94896.jpg|images/67eaeb8e8af1df4c8801df138bbbc56c7763238f3eb5c9f07387ce8202d15f90.jpg; table=table/表 2-1 轴压试件截面明细表.jpg|table/表 3-1 薄壁钢管混凝土轴压试件一览.jpg"
    },
    {
      "ref_no": "",
      "specimen_label": "SCFT16-2",
      "fc_value": 42.8,
      "fc_type": "cube",
      "fy": 140.2,
      "fcy150": "",
      "r_ratio": 0,
      "b": 157.4,
      "h": 162.2,
      "t": 1.9,
      "r0": 0,
      "L": 519.0,
      "e1": 0,
      "e2": 0,
      "n_exp": 957.0,
      "source_evidence": "Page [28], Table [2-1, 3-1]; setup=images/bc93b79be65b77739c8b6e10aa37c9628bed7d4450e4ab3ce3e9965334e94896.jpg|images/67eaeb8e8af1df4c8801df138bbbc56c7763238f3eb5c9f07387ce8202d15f90.jpg; table=table/表 2-1 轴压试件截面明细表.jpg|table/表 3-1 薄壁钢管混凝土轴压试件一览.jpg"
    },
    {
      "ref_no": "",
      "specimen_label": "SCFT16-3",
      "fc_value": 42.8,
      "fc_type": "cube",
      "fy": 140.2,
      "fcy150": "",
      "r_ratio": 0,
      "b": 161.0,
      "h": 161.0,
      "t": 1.9,
      "r0": 0,
      "L": 520.0,
      "e1": 0,
      "e2": 0,
      "n_exp": 1003.0,
      "source_evidence": "Page [28], Table [2-1, 3-1]; setup=images/bc93b79be65b77739c8b6e10aa37c9628bed7d4450e4ab3ce3e9965334e94896.jpg|images/67eaeb8e8af1df4c8801df138bbbc56c7763238f3eb5c9f07387ce8202d15f90.jpg; table=table/表 2-1 轴压试件截面明细表.jpg|table/表 3-1 薄壁钢管混凝土轴压试件一览.jpg"
    },
    {
      "ref_no": "",
      "specimen_label": "SCFT18",
      "fc_value": 57.8,
      "fc_type": "cube",
      "fy": 318.5,
      "fcy150": "",
      "r_ratio": 0,
      "b": 181.8,
      "h": 183.0,
      "t": 1.98,
      "r0": 0,
      "L": 519.0,
      "e1": 0,
      "e2": 0,
      "n_exp": 1312.0,
      "source_evidence": "Page [28], Table [2-1, 3-1]; setup=images/bc93b79be65b77739c8b6e10aa37c9628bed7d4450e4ab3ce3e9965334e94896.jpg|images/67eaeb8e8af1df4c8801df138bbbc56c7763238f3eb5c9f07387ce8202d15f90.jpg; table=table/表 2-1 轴压试件截面明细表.jpg|table/表 3-1 薄壁钢管混凝土轴压试件一览.jpg"
    },
    {
      "ref_no": "",
      "specimen_label": "UCFT20",
      "fc_value": 50.2,
      "fc_type": "cube",
      "fy": 318.5,
      "fcy150": "",
      "r_ratio": 0,
      "b": 200.7,
      "h": 202.5,
      "t": 1.98,
      "r0": 0,
      "L": 636.0,
      "e1": 0,
      "e2": 0,
      "n_exp": 1475.0,
      "source_evidence": "Page [28], Table [2-1, 3-1]; setup=images/bc93b79be65b77739c8b6e10aa37c9628bed7d4450e4ab3ce3e9965334e94896.jpg|images/67eaeb8e8af1df4c8801df138bbbc56c7763238f3eb5c9f07387ce8202d15f90.jpg; table=table/表 2-1 轴压试件截面明细表.jpg|table/表 3-1 薄壁钢管混凝土轴压试件一览.jpg"
    },
    {
      "ref_no": "",
      "specimen_label": "SCFT20-1",
      "fc_value": 57.8,
      "fc_type": "cube",
      "fy": 318.5,
      "fcy150": "",
      "r_ratio": 0,
      "b": 199.4,
      "h": 201.5,
      "t": 1.98,
      "r0": 0,
      "L": 635.0,
      "e1": 0,
      "e2": 0,
      "n_exp": 1471.0,
      "source_evidence": "Page [28], Table [2-1, 3-1]; setup=images/bc93b79be65b77739c8b6e10aa37c9628bed7d4450e4ab3ce3e9965334e94896.jpg|images/67eaeb8e8af1df4c8801df138bbbc56c7763238f3eb5c9f07387ce8202d15f90.jpg; table=table/表 2-1 轴压试件截面明细表.jpg|table/表 3-1 薄壁钢管混凝土轴压试件一览.jpg"
    },
    {
      "ref_no": "",
      "specimen_label": "SCFT20-2",
      "fc_value": 57.8,
      "fc_type": "cube",
      "fy": 318.5,
      "fcy150": "",
      "r_ratio": 0,
      "b": 199.3,
      "h": 202.3,
      "t": 1.98,
      "r0": 0,
      "L": 637.0,
      "e1": 0,
      "e2": 0,
      "n_exp": 1518.0,
      "source_evidence": "Page [28], Table [2-1, 3-1]; setup=images/bc93b79be65b77739c8b6e10aa37c9628bed7d4450e4ab3ce3e9965334e94896.jpg|images/67eaeb8e8af1df4c8801df138bbbc56c7763238f3eb5c9f07387ce8202d15f90.jpg; table=table/表 2-1 轴压试件截面明细表.jpg|table/表 3-1 薄壁钢管混凝土轴压试件一览.jpg"
    },
    {
      "ref_no": "",
      "specimen_label": "SCFT20-3",
      "fc_value": 42.8,
      "fc_type": "cube",
      "fy": 140.8,
      "fcy150": "",
      "r_ratio": 0,
      "b": 199.4,
      "h": 202.0,
      "t": 1.9,
      "r0": 0,
      "L": 639.0,
      "e1": 0,
      "e2": 0,
      "n_exp": 1075.0,
      "source_evidence": "Page [28], Table [2-1, 3-1]; setup=images/bc93b79be65b77739c8b6e10aa37c9628bed7d4450e4ab3ce3e9965334e94896.jpg|images/67eaeb8e8af1df4c8801df138bbbc56c7763238f3eb5c9f07387ce8202d15f90.jpg; table=table/表 2-1 轴压试件截面明细表.jpg|table/表 3-1 薄壁钢管混凝土轴压试件一览.jpg"
    },
    {
      "ref_no": "",
      "specimen_label": "SCFT20-4",
      "fc_value": 42.8,
      "fc_type": "cube",
      "fy": 140.8,
      "fcy150": "",
      "r_ratio": 0,
      "b": 200.1,
      "h": 201.3,
      "t": 1.9,
      "r0": 0,
      "L": 640.0,
      "e1": 0,
      "e2": 0,
      "n_exp": 1086.0,
      "source_evidence": "Page [28], Table [2-1, 3-1]; setup=images/bc93b79be65b77739c8b6e10aa37c9628bed7d4450e4ab3ce3e9965334e94896.jpg|images/67eaeb8e8af1df4c8801df138bbbc56c7763238f3eb5c9f07387ce8202d15f90.jpg; table=table/表 2-1 轴压试件截面明细表.jpg|table/表 3-1 薄壁钢管混凝土轴压试件一览.jpg"
    },
    {
      "ref_no": "",
      "specimen_label": "UCFT1-1",
      "fc_value": 57.8,
      "fc_type": "cube",
      "fy": 318.6,
      "fcy150": "",
      "r_ratio": 0,
      "b": 162.1,
      "h": 199.6,
      "t": 1.98,
      "r0": 0,
      "L": 716.0,
      "e1": 0.0,
      "e2": 0.0,
      "n_exp": 1604.0,
      "source_evidence": "Page [66], Table [2-2, 6-1]; setup=images/552b4346b899a8624527435e1675f7bd26d1b149f21b46eb4289017bb93e6fe3.jpg; table=table/表 2-2 偏压试件截面明细表.jpg|table/表 6-1 薄壁钢管混凝土偏压试件一览.jpg"
    },
    {
      "ref_no": "",
      "specimen_label": "UCFT1-2",
      "fc_value": 57.8,
      "fc_type": "cube",
      "fy": 318.6,
      "fcy150": "",
      "r_ratio": 0,
      "b": 162.6,
      "h": 199.6,
      "t": 1.98,
      "r0": 0,
      "L": 716.0,
      "e1": 26.0,
      "e2": 26.0,
      "n_exp": 1157.0,
      "source_evidence": "Page [66], Table [2-2, 6-1]; setup=images/552b4346b899a8624527435e1675f7bd26d1b149f21b46eb4289017bb93e6fe3.jpg; table=table/表 2-2 偏压试件截面明细表.jpg|table/表 6-1 薄壁钢管混凝土偏压试件一览.jpg"
    },
    {
      "ref_no": "",
      "specimen_label": "UCFT1-3",
      "fc_value": 57.8,
      "fc_type": "cube",
      "fy": 318.6,
      "fcy150": "",
      "r_ratio": 0,
      "b": 162.8,
      "h": 200.9,
      "t": 1.98,
      "r0": 0,
      "L": 716.0,
      "e1": 52.0,
      "e2": 52.0,
      "n_exp": 843.0,
      "source_evidence": "Page [66], Table [2-2, 6-1]; setup=images/552b4346b899a8624527435e1675f7bd26d1b149f21b46eb4289017bb93e6fe3.jpg; table=table/表 2-2 偏压试件截面明细表.jpg|table/表 6-1 薄壁钢管混凝土偏压试件一览.jpg"
    },
    {
      "ref_no": "",
      "specimen_label": "UCFT2-1",
      "fc_value": 57.8,
      "fc_type": "cube",
      "fy": 318.6,
      "fcy150": "",
      "r_ratio": 0,
      "b": 160.8,
      "h": 162.1,
      "t": 1.98,
      "r0": 0,
      "L": 716.0,
      "e1": 26.0,
      "e2": 26.0,
      "n_exp": 1001.0,
      "source_evidence": "Page [66], Table [2-2, 6-1]; setup=images/552b4346b899a8624527435e1675f7bd26d1b149f21b46eb4289017bb93e6fe3.jpg; table=table/表 2-2 偏压试件截面明细表.jpg|table/表 6-1 薄壁钢管混凝土偏压试件一览.jpg"
    },
    {
      "ref_no": "",
      "specimen_label": "UCFT3-1",
      "fc_value": 57.8,
      "fc_type": "cube",
      "fy": 318.6,
      "fcy150": "",
      "r_ratio": 0,
      "b": 163.3,
      "h": 241.0,
      "t": 1.98,
      "r0": 0,
      "L": 716.0,
      "e1": 26.0,
      "e2": 26.0,
      "n_exp": 1416.0,
      "source_evidence": "Page [66], Table [2-2, 6-1]; setup=images/552b4346b899a8624527435e1675f7bd26d1b149f21b46eb4289017bb93e6fe3.jpg; table=table/表 2-2 偏压试件截面明细表.jpg|table/表 6-1 薄壁钢管混凝土偏压试件一览.jpg"
    },
    {
      "ref_no": "",
      "specimen_label": "SCFT1-1",
      "fc_value": 57.8,
      "fc_type": "cube",
      "fy": 318.6,
      "fcy150": "",
      "r_ratio": 0,
      "b": 162.8,
      "h": 202.8,
      "t": 1.98,
      "r0": 0,
      "L": 716.0,
      "e1": 0.0,
      "e2": 0.0,
      "n_exp": 1628.0,
      "source_evidence": "Page [66], Table [2-2, 6-1]; setup=images/552b4346b899a8624527435e1675f7bd26d1b149f21b46eb4289017bb93e6fe3.jpg; table=table/表 2-2 偏压试件截面明细表.jpg|table/表 6-1 薄壁钢管混凝土偏压试件一览.jpg"
    },
    {
      "ref_no": "",
      "specimen_label": "SCFT1-2",
      "fc_value": 57.8,
      "fc_type": "cube",
      "fy": 318.6,
      "fcy150": "",
      "r_ratio": 0,
      "b": 162.4,
      "h": 202.3,
      "t": 1.98,
      "r0": 0,
      "L": 716.0,
      "e1": 26.0,
      "e2": 26.0,
      "n_exp": 1313.0,
      "source_evidence": "Page [66], Table [2-2, 6-1]; setup=images/552b4346b899a8624527435e1675f7bd26d1b149f21b46eb4289017bb93e6fe3.jpg; table=table/表 2-2 偏压试件截面明细表.jpg|table/表 6-1 薄壁钢管混凝土偏压试件一览.jpg"
    },
    {
      "ref_no": "",
      "specimen_label": "SCFT1-3",
      "fc_value": 57.8,
      "fc_type": "cube",
      "fy": 318.6,
      "fcy150": "",
      "r_ratio": 0,
      "b": 163.0,
      "h": 200.4,
      "t": 1.98,
      "r0": 0,
      "L": 716.0,
      "e1": 52.0,
      "e2": 52.0,
      "n_exp": 1051.0,
      "source_evidence": "Page [66], Table [2-2, 6-1]; setup=images/552b4346b899a8624527435e1675f7bd26d1b149f21b46eb4289017bb93e6fe3.jpg; table=table/表 2-2 偏压试件截面明细表.jpg|table/表 6-1 薄壁钢管混凝土偏压试件一览.jpg"
    },
    {
      "ref_no": "",
      "specimen_label": "SCFT2-1",
      "fc_value": 42.8,
      "fc_type": "cube",
      "fy": 140.2,
      "fcy150": "",
      "r_ratio": 0,
      "b": 199.4,
      "h": 202.0,
      "t": 1.9,
      "r0": 0,
      "L": 720.0,
      "e1": 0.0,
      "e2": 0.0,
      "n_exp": 1154.0,
      "source_evidence": "Page [66], Table [2-2, 6-1]; setup=images/552b4346b899a8624527435e1675f7bd26d1b149f21b46eb4289017bb93e6fe3.jpg; table=table/表 2-2 偏压试件截面明细表.jpg|table/表 6-1 薄壁钢管混凝土偏压试件一览.jpg"
    },
    {
      "ref_no": "",
      "specimen_label": "SCFT2-2",
      "fc_value": 42.8,
      "fc_type": "cube",
      "fy": 140.2,
      "fcy150": "",
      "r_ratio": 0,
      "b": 160.7,
      "h": 201.0,
      "t": 1.9,
      "r0": 0,
      "L": 719.0,
      "e1": 26.0,
      "e2": 26.0,
      "n_exp": 874.0,
      "source_evidence": "Page [66], Table [2-2, 6-1]; setup=images/552b4346b899a8624527435e1675f7bd26d1b149f21b46eb4289017bb93e6fe3.jpg; table=table/表 2-2 偏压试件截面明细表.jpg|table/表 6-1 薄壁钢管混凝土偏压试件一览.jpg"
    },
    {
      "ref_no": "",
      "specimen_label": "SCFT2-3",
      "fc_value": 42.8,
      "fc_type": "cube",
      "fy": 301.8,
      "fcy150": "",
      "r_ratio": 0,
      "b": 160.1,
      "h": 199.0,
      "t": 1.9,
      "r0": 0,
      "L": 718.0,
      "e1": 52.0,
      "e2": 52.0,
      "n_exp": 691.0,
      "source_evidence": "Page [66], Table [2-2, 6-1]; setup=images/552b4346b899a8624527435e1675f7bd26d1b149f21b46eb4289017bb93e6fe3.jpg; table=table/表 2-2 偏压试件截面明细表.jpg|table/表 6-1 薄壁钢管混凝土偏压试件一览.jpg"
    }
  ],
  "Group_B": [],
  "Group_C": []
}