{
  "is_valid": true,
  "reason": "Valid CFST axial-compression experiment paper; extracted complete specimen rows from Tab. 1 and excluded RCFSST4-30 because Pue is missing in source table.",
  "ref_info": {
    "title": "Experiment on mechanical behavior of recycled aggregate concrete-filled square steel tubular short columns under axial compression",
    "authors": [
      "ZHANG Ji-cheng",
      "SHEN Xing-yue",
      "WANG Jing-feng",
      "DU Guo-feng",
      "WANG Ke-hui"
    ],
    "journal": "Unknown",
    "year": 2016
  },
  "Group_A": [
    {
      "ref_no": "",
      "specimen_label": "RCFSST3-00",
      "fc_value": 51.02,
      "fc_type": "Unknown",
      "fy": 336,
      "fcy150": "",
      "r_ratio": 0,
      "b": 150,
      "h": 150,
      "t": 2.6,
      "r0": 0,
      "L": 450,
      "e1": 0,
      "e2": 0,
      "n_exp": 1751,
      "source_evidence": "Page [3], Table [Tab. 1 Basic parameters of tested specimens]; setup=images/629d038b78d3928d2c3b15fd6768f4cc5e9183bbf579112778abbcc92286839a.jpg; table=table/Tab. 1 Basic parameters of tested specimens.jpg"
    },
    {
      "ref_no": "",
      "specimen_label": "RCFSST4-00",
      "fc_value": 51.02,
      "fc_type": "Unknown",
      "fy": 342,
      "fcy150": "",
      "r_ratio": 0,
      "b": 150,
      "h": 150,
      "t": 3.6,
      "r0": 0,
      "L": 450,
      "e1": 0,
      "e2": 0,
      "n_exp": 1881,
      "source_evidence": "Page [3], Table [Tab. 1 Basic parameters of tested specimens]; setup=images/629d038b78d3928d2c3b15fd6768f4cc5e9183bbf579112778abbcc92286839a.jpg; table=table/Tab. 1 Basic parameters of tested specimens.jpg"
    },
    {
      "ref_no": "",
      "specimen_label": "RCFSST5-00",
      "fc_value": 51.02,
      "fc_type": "Unknown",
      "fy": 338,
      "fcy150": "",
      "r_ratio": 0,
      "b": 150,
      "h": 150,
      "t": 4.5,
      "r0": 0,
      "L": 450,
      "e1": 0,
      "e2": 0,
      "n_exp": 2004,
      "source_evidence": "Page [3], Table [Tab. 1 Basic parameters of tested specimens]; setup=images/629d038b78d3928d2c3b15fd6768f4cc5e9183bbf579112778abbcc92286839a.jpg; table=table/Tab. 1 Basic parameters of tested specimens.jpg"
    },
    {
      "ref_no": "",
      "specimen_label": "RCFSST3-30",
      "fc_value": 50.12,
      "fc_type": "Unknown",
      "fy": 336,
      "fcy150": "",
      "r_ratio": 30,
      "b": 150,
      "h": 150,
      "t": 2.6,
      "r0": 0,
      "L": 450,
      "e1": 0,
      "e2": 0,
      "n_exp": 1644,
      "source_evidence": "Page [3], Table [Tab. 1 Basic parameters of tested specimens]; setup=images/629d038b78d3928d2c3b15fd6768f4cc5e9183bbf579112778abbcc92286839a.jpg; table=table/Tab. 1 Basic parameters of tested specimens.jpg"
    },
    {
      "ref_no": "",
      "specimen_label": "RCFSST5-30",
      "fc_value": 50.12,
      "fc_type": "Unknown",
      "fy": 338,
      "fcy150": "",
      "r_ratio": 30,
      "b": 150,
      "h": 150,
      "t": 4.5,
      "r0": 0,
      "L": 450,
      "e1": 0,
      "e2": 0,
      "n_exp": 1962,
      "source_evidence": "Page [3], Table [Tab. 1 Basic parameters of tested specimens]; setup=images/629d038b78d3928d2c3b15fd6768f4cc5e9183bbf579112778abbcc92286839a.jpg; table=table/Tab. 1 Basic parameters of tested specimens.jpg"
    },
    {
      "ref_no": "",
      "specimen_label": "RCFSST3-60",
      "fc_value": 49.71,
      "fc_type": "Unknown",
      "fy": 336,
      "fcy150": "",
      "r_ratio": 60,
      "b": 150,
      "h": 150,
      "t": 2.6,
      "r0": 0,
      "L": 450,
      "e1": 0,
      "e2": 0,
      "n_exp": 1545,
      "source_evidence": "Page [3], Table [Tab. 1 Basic parameters of tested specimens]; setup=images/629d038b78d3928d2c3b15fd6768f4cc5e9183bbf579112778abbcc92286839a.jpg; table=table/Tab. 1 Basic parameters of tested specimens.jpg"
    },
    {
      "ref_no": "",
      "specimen_label": "RCFSST4-60",
      "fc_value": 49.71,
      "fc_type": "Unknown",
      "fy": 342,
      "fcy150": "",
      "r_ratio": 60,
      "b": 150,
      "h": 150,
      "t": 3.6,
      "r0": 0,
      "L": 450,
      "e1": 0,
      "e2": 0,
      "n_exp": 1841,
      "source_evidence": "Page [3], Table [Tab. 1 Basic parameters of tested specimens]; setup=images/629d038b78d3928d2c3b15fd6768f4cc5e9183bbf579112778abbcc92286839a.jpg; table=table/Tab. 1 Basic parameters of tested specimens.jpg"
    },
    {
      "ref_no": "",
      "specimen_label": "RCFSST5-60",
      "fc_value": 49.71,
      "fc_type": "Unknown",
      "fy": 338,
      "fcy150": "",
      "r_ratio": 60,
      "b": 150,
      "h": 150,
      "t": 4.5,
      "r0": 0,
      "L": 450,
      "e1": 0,
      "e2": 0,
      "n_exp": 1860,
      "source_evidence": "Page [3], Table [Tab. 1 Basic parameters of tested specimens]; setup=images/629d038b78d3928d2c3b15fd6768f4cc5e9183bbf579112778abbcc92286839a.jpg; table=table/Tab. 1 Basic parameters of tested specimens.jpg"
    }
  ],
  "Group_B": [],
  "Group_C": []
}
