{
  "is_valid": true,
  "reason": "Valid CFST stub-column physical tests under concentric axial compression; specimen properties and ultimate loads are reported in Tables 2.1 and 2.6.",
  "ref_info": {
    "title": "钢管混凝土轴心受压短柱试验及数值模拟研究",
    "authors": ["龙小波"],
    "journal": "Unknown",
    "year": 2014
  },
  "Group_A": [],
  "Group_B": [
    {
      "ref_no": "",
      "specimen_label": "C1-50",
      "fc_value": 54.3,
      "fc_type": "Cube 150",
      "fy": 593.2,
      "fcy150": "",
      "r_ratio": 0,
      "b": 146,
      "h": 146,
      "t": 3,
      "r0": 73.0,
      "L": 350,
      "e1": 0,
      "e2": 0,
      "n_exp": 2006,
      "source_evidence": "Page [13, 19], Table [2.1, 2.6], Figure [2.4]; setup=images/a61c200dd3dc54f7b9397e7f6cd8ba064de2a5682ec663a3037b41fdf4534a5c.jpg; table=table/表 2.1 试件一览表.jpg; table=table/表 2.6 钢管混凝土轴压短柱试验结果.jpg"
    },
    {
      "ref_no": "",
      "specimen_label": "C1-30",
      "fc_value": 34.6,
      "fc_type": "Cube 150",
      "fy": 593.2,
      "fcy150": "",
      "r_ratio": 0,
      "b": 146,
      "h": 146,
      "t": 3,
      "r0": 73.0,
      "L": 350,
      "e1": 0,
      "e2": 0,
      "n_exp": 1735,
      "source_evidence": "Page [13, 19], Table [2.1, 2.6], Figure [2.4]; setup=images/a61c200dd3dc54f7b9397e7f6cd8ba064de2a5682ec663a3037b41fdf4534a5c.jpg; table=table/表 2.1 试件一览表.jpg; table=table/表 2.6 钢管混凝土轴压短柱试验结果.jpg"
    },
    {
      "ref_no": "",
      "specimen_label": "C2-50",
      "fc_value": 54.3,
      "fc_type": "Cube 150",
      "fy": 594.5,
      "fcy150": "",
      "r_ratio": 0,
      "b": 150,
      "h": 150,
      "t": 5,
      "r0": 75.0,
      "L": 350,
      "e1": 0,
      "e2": 0,
      "n_exp": 2586,
      "source_evidence": "Page [13, 19], Table [2.1, 2.6], Figure [2.4]; setup=images/a61c200dd3dc54f7b9397e7f6cd8ba064de2a5682ec663a3037b41fdf4534a5c.jpg; table=table/表 2.1 试件一览表.jpg; table=table/表 2.6 钢管混凝土轴压短柱试验结果.jpg"
    },
    {
      "ref_no": "",
      "specimen_label": "C2-30",
      "fc_value": 34.6,
      "fc_type": "Cube 150",
      "fy": 594.5,
      "fcy150": "",
      "r_ratio": 0,
      "b": 150,
      "h": 150,
      "t": 5,
      "r0": 75.0,
      "L": 350,
      "e1": 0,
      "e2": 0,
      "n_exp": 2362,
      "source_evidence": "Page [13, 19], Table [2.1, 2.6], Figure [2.4]; setup=images/a61c200dd3dc54f7b9397e7f6cd8ba064de2a5682ec663a3037b41fdf4534a5c.jpg; table=table/表 2.1 试件一览表.jpg; table=table/表 2.6 钢管混凝土轴压短柱试验结果.jpg"
    },
    {
      "ref_no": "",
      "specimen_label": "C3-50",
      "fc_value": 54.3,
      "fc_type": "Cube 150",
      "fy": 593.5,
      "fcy150": "",
      "r_ratio": 0,
      "b": 154,
      "h": 154,
      "t": 7,
      "r0": 77.0,
      "L": 350,
      "e1": 0,
      "e2": 0,
      "n_exp": 3198,
      "source_evidence": "Page [13, 19], Table [2.1, 2.6], Figure [2.4]; setup=images/a61c200dd3dc54f7b9397e7f6cd8ba064de2a5682ec663a3037b41fdf4534a5c.jpg; table=table/表 2.1 试件一览表.jpg; table=table/表 2.6 钢管混凝土轴压短柱试验结果.jpg"
    },
    {
      "ref_no": "",
      "specimen_label": "C3-30",
      "fc_value": 34.6,
      "fc_type": "Cube 150",
      "fy": 593.5,
      "fcy150": "",
      "r_ratio": 0,
      "b": 154,
      "h": 154,
      "t": 7,
      "r0": 77.0,
      "L": 350,
      "e1": 0,
      "e2": 0,
      "n_exp": 2955,
      "source_evidence": "Page [13, 19], Table [2.1, 2.6], Figure [2.4]; setup=images/a61c200dd3dc54f7b9397e7f6cd8ba064de2a5682ec663a3037b41fdf4534a5c.jpg; table=table/表 2.1 试件一览表.jpg; table=table/表 2.6 钢管混凝土轴压短柱试验结果.jpg"
    }
  ],
  "Group_C": []
}
